sacred/__init__.py
sacred_tui-0.2.dist-info/METADATA
sacred_tui-0.2.dist-info/RECORD
sacred_tui-0.2.dist-info/WHEEL
sacred_tui-0.2.dist-info/entry_points.txt
sacred_tui-0.2.dist-info/top_level.txt
