Metadata-Version: 2.1
Name: sacred-tui
Version: 0.2
Summary: Python library for ASCII art import and TUI development
Home-page: https://github.com/justaboredkid/sacred
Author: justaboredkid
Author-email: 29010153+justaboredkid@users.noreply.github.com
License: GNU GPLv3
Platform: UNKNOWN
Classifier: License :: OSI Approved :: GNU General Public License v3 (GPLv3)
Classifier: Programming Language :: Python :: 3
Requires-Dist: blessed
